{
  "version": "1.0.0",
  "description": "IDL Registry for Solana Protocols",
  "lastUpdated": "2025-10-09T14:04:53.373481",
  "totalProtocols": 102,
  "categories": [
    "defi",
    "derivatives",
    "dex",
    "dex-aggregator",
    "launchpad",
    "lending",
    "liquid-staking",
    "trading"
  ],
  "protocols": [
    {
      "id": "idl-protocol",
      "name": "IDL Protocol",
      "description": "$IDL Token Protocol - Staking, Prediction Markets, OHM-style Tokenomics",
      "category": "defi",
      "idlPath": "IDLs/idl-protocolIDL.json",
      "repo": "https://github.com/openSVM/idlhub",
      "status": "available",
      "version": "0.1.0",
      "lastUpdated": "2025-12-17"
    },
    {
      "id": "acceleraytor",
      "name": "Acceleraytor",
      "description": "Solana launchpad platform",
      "category": "launchpad",
      "idlPath": "IDLs/acceleraytorIDL.json",
      "repo": null,
      "status": "placeholder",
      "version": "0.1.0",
      "lastUpdated": "2025-10-09"
    },
    {
      "id": "adrena",
      "name": "Adrena",
      "description": "Decentralized trading platform",
      "category": "trading",
      "idlPath": "IDLs/adrenaIDL.json",
      "repo": null,
      "status": "placeholder",
      "version": "0.1.0",
      "lastUpdated": "2025-10-09"
    },
    {
      "id": "aldrin",
      "name": "Aldrin",
      "description": "AMM and DEX on Solana",
      "category": "dex",
      "idlPath": "IDLs/aldrinIDL.json",
      "repo": null,
      "status": "available",
      "version": "0.1.0",
      "lastUpdated": "2025-10-09"
    },
    {
      "id": "apricot",
      "name": "Apricot",
      "description": "apricot protocol on Solana",
      "category": "defi",
      "idlPath": "IDLs/apricotIDL.json",
      "repo": null,
      "status": "available",
      "version": "0.1.0",
      "lastUpdated": "2025-10-09"
    },
    {
      "id": "arrow",
      "name": "Arrow",
      "description": "arrow protocol on Solana",
      "category": "defi",
      "idlPath": "IDLs/arrowIDL.json",
      "repo": null,
      "status": "available",
      "version": "0.1.0",
      "lastUpdated": "2025-10-09"
    },
    {
      "id": "atrix",
      "name": "Atrix",
      "description": "atrix protocol on Solana",
      "category": "defi",
      "idlPath": "IDLs/atrixIDL.json",
      "repo": null,
      "status": "available",
      "version": "0.1.0",
      "lastUpdated": "2025-10-09"
    },
    {
      "id": "balansol",
      "name": "Balansol",
      "description": "balansol protocol on Solana",
      "category": "defi",
      "idlPath": "IDLs/balansolIDL.json",
      "repo": null,
      "status": "placeholder",
      "version": "0.1.0",
      "lastUpdated": "2025-10-09"
    },
    {
      "id": "beluga",
      "name": "Beluga",
      "description": "beluga protocol on Solana",
      "category": "defi",
      "idlPath": "IDLs/belugaIDL.json",
      "repo": null,
      "status": "placeholder",
      "version": "0.1.0",
      "lastUpdated": "2025-10-09"
    },
    {
      "id": "blaze",
      "name": "Blaze",
      "description": "blaze protocol on Solana",
      "category": "defi",
      "idlPath": "IDLs/blazeIDL.json",
      "repo": null,
      "status": "placeholder",
      "version": "0.1.0",
      "lastUpdated": "2025-10-09"
    },
    {
      "id": "bonfida",
      "name": "Bonfida",
      "description": "bonfida protocol on Solana",
      "category": "defi",
      "idlPath": "IDLs/bonfidaIDL.json",
      "repo": null,
      "status": "available",
      "version": "0.1.0",
      "lastUpdated": "2025-10-09"
    },
    {
      "id": "byreal",
      "name": "Byreal",
      "description": "byreal protocol on Solana",
      "category": "defi",
      "idlPath": "IDLs/byrealIDL.json",
      "repo": null,
      "status": "placeholder",
      "version": "0.1.0",
      "lastUpdated": "2025-10-09"
    },
    {
      "id": "cashio",
      "name": "Cashio",
      "description": "cashio protocol on Solana",
      "category": "defi",
      "idlPath": "IDLs/cashioIDL.json",
      "repo": null,
      "status": "placeholder",
      "version": "0.1.0",
      "lastUpdated": "2025-10-09"
    },
    {
      "id": "clone",
      "name": "Clone",
      "description": "clone protocol on Solana",
      "category": "defi",
      "idlPath": "IDLs/cloneIDL.json",
      "repo": null,
      "status": "placeholder",
      "version": "0.1.0",
      "lastUpdated": "2025-10-09"
    },
    {
      "id": "crate",
      "name": "Crate",
      "description": "crate protocol on Solana",
      "category": "defi",
      "idlPath": "IDLs/crateIDL.json",
      "repo": null,
      "status": "placeholder",
      "version": "0.1.0",
      "lastUpdated": "2025-10-09"
    },
    {
      "id": "crema",
      "name": "Crema",
      "description": "crema protocol on Solana",
      "category": "defi",
      "idlPath": "IDLs/cremaIDL.json",
      "repo": null,
      "status": "available",
      "version": "0.1.0",
      "lastUpdated": "2025-10-09"
    },
    {
      "id": "cropper",
      "name": "Cropper",
      "description": "cropper protocol on Solana",
      "category": "defi",
      "idlPath": "IDLs/cropperIDL.json",
      "repo": null,
      "status": "placeholder",
      "version": "0.1.0",
      "lastUpdated": "2025-10-09"
    },
    {
      "id": "cyclos",
      "name": "Cyclos",
      "description": "cyclos protocol on Solana",
      "category": "defi",
      "idlPath": "IDLs/cyclosIDL.json",
      "repo": null,
      "status": "available",
      "version": "0.1.0",
      "lastUpdated": "2025-10-09"
    },
    {
      "id": "cykura",
      "name": "Cykura",
      "description": "cykura protocol on Solana",
      "category": "defi",
      "idlPath": "IDLs/cykuraIDL.json",
      "repo": null,
      "status": "available",
      "version": "0.1.0",
      "lastUpdated": "2025-10-09"
    },
    {
      "id": "deltaone",
      "name": "Deltaone",
      "description": "deltaone protocol on Solana",
      "category": "defi",
      "idlPath": "IDLs/deltaoneIDL.json",
      "repo": null,
      "status": "placeholder",
      "version": "0.1.0",
      "lastUpdated": "2025-10-09"
    },
    {
      "id": "dexlab",
      "name": "Dexlab",
      "description": "dexlab protocol on Solana",
      "category": "defi",
      "idlPath": "IDLs/dexlabIDL.json",
      "repo": null,
      "status": "available",
      "version": "0.1.0",
      "lastUpdated": "2025-10-09"
    },
    {
      "id": "dexterity",
      "name": "Dexterity",
      "description": "dexterity protocol on Solana",
      "category": "defi",
      "idlPath": "IDLs/dexterityIDL.json",
      "repo": null,
      "status": "available",
      "version": "0.1.0",
      "lastUpdated": "2025-10-09"
    },
    {
      "id": "drift",
      "name": "Drift Protocol",
      "description": "Decentralized perpetual futures exchange",
      "category": "derivatives",
      "idlPath": "IDLs/driftIDL.json",
      "repo": "https://github.com/drift-labs/protocol-v2",
      "status": "available",
      "version": "0.1.0",
      "lastUpdated": "2025-10-09"
    },
    {
      "id": "ellipsis",
      "name": "Ellipsis",
      "description": "ellipsis protocol on Solana",
      "category": "defi",
      "idlPath": "IDLs/ellipsisIDL.json",
      "repo": null,
      "status": "placeholder",
      "version": "0.1.0",
      "lastUpdated": "2025-10-09"
    },
    {
      "id": "enjinstarter",
      "name": "Enjinstarter",
      "description": "enjinstarter protocol on Solana",
      "category": "defi",
      "idlPath": "IDLs/enjinstarterIDL.json",
      "repo": null,
      "status": "placeholder",
      "version": "0.1.0",
      "lastUpdated": "2025-10-09"
    },
    {
      "id": "flash",
      "name": "Flash",
      "description": "flash protocol on Solana",
      "category": "defi",
      "idlPath": "IDLs/flashIDL.json",
      "repo": null,
      "status": "placeholder",
      "version": "0.1.0",
      "lastUpdated": "2025-10-09"
    },
    {
      "id": "fluxbeam",
      "name": "Fluxbeam",
      "description": "fluxbeam protocol on Solana",
      "category": "defi",
      "idlPath": "IDLs/fluxbeamIDL.json",
      "repo": null,
      "status": "available",
      "version": "0.1.0",
      "lastUpdated": "2025-10-09"
    },
    {
      "id": "francium",
      "name": "Francium",
      "description": "francium protocol on Solana",
      "category": "defi",
      "idlPath": "IDLs/franciumIDL.json",
      "repo": null,
      "status": "available",
      "version": "0.1.0",
      "lastUpdated": "2025-10-09"
    },
    {
      "id": "gauge",
      "name": "Gauge",
      "description": "gauge protocol on Solana",
      "category": "defi",
      "idlPath": "IDLs/gaugeIDL.json",
      "repo": null,
      "status": "placeholder",
      "version": "0.1.0",
      "lastUpdated": "2025-10-09"
    },
    {
      "id": "gavel",
      "name": "Gavel",
      "description": "gavel protocol on Solana",
      "category": "defi",
      "idlPath": "IDLs/gavelIDL.json",
      "repo": null,
      "status": "placeholder",
      "version": "0.1.0",
      "lastUpdated": "2025-10-09"
    },
    {
      "id": "gmx",
      "name": "Gmx",
      "description": "gmx protocol on Solana",
      "category": "defi",
      "idlPath": "IDLs/gmxIDL.json",
      "repo": null,
      "status": "placeholder",
      "version": "0.1.0",
      "lastUpdated": "2025-10-09"
    },
    {
      "id": "goki",
      "name": "Goki",
      "description": "goki protocol on Solana",
      "category": "defi",
      "idlPath": "IDLs/gokiIDL.json",
      "repo": null,
      "status": "available",
      "version": "0.1.0",
      "lastUpdated": "2025-10-09"
    },
    {
      "id": "goonfi",
      "name": "Goonfi",
      "description": "goonfi protocol on Solana",
      "category": "defi",
      "idlPath": "IDLs/goonfiIDL.json",
      "repo": null,
      "status": "placeholder",
      "version": "0.1.0",
      "lastUpdated": "2025-10-09"
    },
    {
      "id": "goosefx",
      "name": "Goosefx",
      "description": "goosefx protocol on Solana",
      "category": "defi",
      "idlPath": "IDLs/goosefxIDL.json",
      "repo": null,
      "status": "available",
      "version": "0.1.0",
      "lastUpdated": "2025-10-09"
    },
    {
      "id": "hawksight",
      "name": "Hawksight",
      "description": "hawksight protocol on Solana",
      "category": "defi",
      "idlPath": "IDLs/hawksightIDL.json",
      "repo": null,
      "status": "placeholder",
      "version": "0.1.0",
      "lastUpdated": "2025-10-09"
    },
    {
      "id": "hubble",
      "name": "Hubble",
      "description": "hubble protocol on Solana",
      "category": "defi",
      "idlPath": "IDLs/hubbleIDL.json",
      "repo": null,
      "status": "available",
      "version": "0.1.0",
      "lastUpdated": "2025-10-09"
    },
    {
      "id": "humidifi",
      "name": "Humidifi",
      "description": "humidifi protocol on Solana",
      "category": "defi",
      "idlPath": "IDLs/humidifiIDL.json",
      "repo": null,
      "status": "placeholder",
      "version": "0.1.0",
      "lastUpdated": "2025-10-09"
    },
    {
      "id": "hxro",
      "name": "Hxro",
      "description": "hxro protocol on Solana",
      "category": "defi",
      "idlPath": "IDLs/hxroIDL.json",
      "repo": null,
      "status": "available",
      "version": "0.1.0",
      "lastUpdated": "2025-10-09"
    },
    {
      "id": "invariant",
      "name": "Invariant",
      "description": "invariant protocol on Solana",
      "category": "defi",
      "idlPath": "IDLs/invariantIDL.json",
      "repo": null,
      "status": "available",
      "version": "0.1.0",
      "lastUpdated": "2025-10-09"
    },
    {
      "id": "jet",
      "name": "Jet",
      "description": "jet protocol on Solana",
      "category": "defi",
      "idlPath": "IDLs/jetIDL.json",
      "repo": null,
      "status": "available",
      "version": "0.1.0",
      "lastUpdated": "2025-10-09"
    },
    {
      "id": "jito",
      "name": "Jito",
      "description": "MEV and liquid staking",
      "category": "liquid-staking",
      "idlPath": "IDLs/jitoIDL.json",
      "repo": null,
      "status": "available",
      "version": "0.1.0",
      "lastUpdated": "2025-10-09"
    },
    {
      "id": "jupiter",
      "name": "Jupiter",
      "description": "Jupiter Aggregator - The key liquidity aggregator for Solana",
      "category": "dex-aggregator",
      "idlPath": "IDLs/jupiterIDL.json",
      "repo": "https://github.com/jup-ag/jupiter-core",
      "status": "available",
      "version": "0.1.0",
      "lastUpdated": "2025-10-09"
    },
    {
      "id": "kamino",
      "name": "Kamino",
      "description": "Automated liquidity management and lending protocol",
      "category": "lending",
      "idlPath": "IDLs/kaminoIDL.json",
      "repo": "https://github.com/Kamino-Finance/klend-sdk",
      "status": "available",
      "version": "1.12.6",
      "lastUpdated": "2024-12-17"
    },
    {
      "id": "larix",
      "name": "Larix",
      "description": "larix protocol on Solana",
      "category": "defi",
      "idlPath": "IDLs/larixIDL.json",
      "repo": null,
      "status": "available",
      "version": "0.1.0",
      "lastUpdated": "2025-10-09"
    },
    {
      "id": "launchmynft",
      "name": "Launchmynft",
      "description": "launchmynft protocol on Solana",
      "category": "defi",
      "idlPath": "IDLs/launchmynftIDL.json",
      "repo": null,
      "status": "placeholder",
      "version": "0.1.0",
      "lastUpdated": "2025-10-09"
    },
    {
      "id": "lifinity",
      "name": "Lifinity",
      "description": "lifinity protocol on Solana",
      "category": "defi",
      "idlPath": "IDLs/lifinityIDL.json",
      "repo": null,
      "status": "available",
      "version": "0.1.0",
      "lastUpdated": "2025-10-09"
    },
    {
      "id": "lifinity-v2",
      "name": "Lifinity v2",
      "description": "lifinity-v2 protocol on Solana",
      "category": "defi",
      "idlPath": "IDLs/lifinity-v2IDL.json",
      "repo": null,
      "status": "available",
      "version": "0.1.0",
      "lastUpdated": "2025-10-09"
    },
    {
      "id": "magiceden",
      "name": "Magiceden",
      "description": "magiceden protocol on Solana",
      "category": "defi",
      "idlPath": "IDLs/magicedenIDL.json",
      "repo": null,
      "status": "available",
      "version": "0.1.0",
      "lastUpdated": "2025-10-09"
    },
    {
      "id": "mango",
      "name": "Mango Markets",
      "description": "Decentralized trading platform",
      "category": "dex",
      "idlPath": "IDLs/mangoIDL.json",
      "repo": null,
      "status": "available",
      "version": "0.1.0",
      "lastUpdated": "2025-10-09"
    },
    {
      "id": "mango-v3",
      "name": "Mango v3",
      "description": "mango-v3 protocol on Solana",
      "category": "defi",
      "idlPath": "IDLs/mango-v3IDL.json",
      "repo": null,
      "status": "available",
      "version": "0.1.0",
      "lastUpdated": "2025-10-09"
    },
    {
      "id": "marginfi",
      "name": "MarginFi",
      "description": "Decentralized lending protocol",
      "category": "lending",
      "idlPath": "IDLs/marginfiIDL.json",
      "repo": null,
      "status": "available",
      "version": "0.1.0",
      "lastUpdated": "2025-10-09"
    },
    {
      "id": "marinade",
      "name": "Marinade Finance",
      "description": "Liquid staking protocol for Solana",
      "category": "liquid-staking",
      "idlPath": "IDLs/marinadeIDL.json",
      "repo": "https://github.com/marinade-finance/liquid-staking-program",
      "status": "available",
      "version": "0.1.0",
      "lastUpdated": "2025-10-09"
    },
    {
      "id": "mercurial",
      "name": "Mercurial",
      "description": "mercurial protocol on Solana",
      "category": "defi",
      "idlPath": "IDLs/mercurialIDL.json",
      "repo": null,
      "status": "available",
      "version": "0.1.0",
      "lastUpdated": "2025-10-09"
    },
    {
      "id": "merkle-distributor",
      "name": "Merkle distributor",
      "description": "merkle-distributor protocol on Solana",
      "category": "defi",
      "idlPath": "IDLs/merkle-distributorIDL.json",
      "repo": null,
      "status": "placeholder",
      "version": "0.1.0",
      "lastUpdated": "2025-10-09"
    },
    {
      "id": "meteora",
      "name": "Meteora",
      "description": "Dynamic liquidity protocol",
      "category": "dex",
      "idlPath": "IDLs/meteoraIDL.json",
      "repo": null,
      "status": "available",
      "version": "0.1.0",
      "lastUpdated": "2025-10-09"
    },
    {
      "id": "obric",
      "name": "Obric",
      "description": "obric protocol on Solana",
      "category": "defi",
      "idlPath": "IDLs/obricIDL.json",
      "repo": null,
      "status": "placeholder",
      "version": "0.1.0",
      "lastUpdated": "2025-10-09"
    },
    {
      "id": "openbook",
      "name": "OpenBook",
      "description": "Order book DEX (Serum fork)",
      "category": "dex",
      "idlPath": "IDLs/openbookIDL.json",
      "repo": null,
      "status": "available",
      "version": "0.1.0",
      "lastUpdated": "2025-10-09"
    },
    {
      "id": "orca",
      "name": "Orca (Whirlpool)",
      "description": "Orca's concentrated liquidity AMM",
      "category": "dex",
      "idlPath": "IDLs/orcaIDL.json",
      "repo": "https://github.com/orca-so/whirlpools",
      "status": "available",
      "version": "0.1.0",
      "lastUpdated": "2025-10-09"
    },
    {
      "id": "parrot",
      "name": "Parrot",
      "description": "parrot protocol on Solana",
      "category": "defi",
      "idlPath": "IDLs/parrotIDL.json",
      "repo": null,
      "status": "placeholder",
      "version": "0.1.0",
      "lastUpdated": "2025-10-09"
    },
    {
      "id": "penguin",
      "name": "Penguin",
      "description": "penguin protocol on Solana",
      "category": "defi",
      "idlPath": "IDLs/penguinIDL.json",
      "repo": null,
      "status": "placeholder",
      "version": "0.1.0",
      "lastUpdated": "2025-10-09"
    },
    {
      "id": "permalock",
      "name": "Permalock",
      "description": "permalock protocol on Solana",
      "category": "defi",
      "idlPath": "IDLs/permalockIDL.json",
      "repo": null,
      "status": "placeholder",
      "version": "0.1.0",
      "lastUpdated": "2025-10-09"
    },
    {
      "id": "phoenix",
      "name": "Phoenix",
      "description": "Order book DEX",
      "category": "dex",
      "idlPath": "IDLs/phoenixIDL.json",
      "repo": null,
      "status": "available",
      "version": "0.1.0",
      "lastUpdated": "2025-10-09"
    },
    {
      "id": "plasma",
      "name": "Plasma",
      "description": "plasma protocol on Solana",
      "category": "defi",
      "idlPath": "IDLs/plasmaIDL.json",
      "repo": null,
      "status": "placeholder",
      "version": "0.1.0",
      "lastUpdated": "2025-10-09"
    },
    {
      "id": "pool-manager",
      "name": "Pool manager",
      "description": "pool-manager protocol on Solana",
      "category": "defi",
      "idlPath": "IDLs/pool-managerIDL.json",
      "repo": null,
      "status": "placeholder",
      "version": "0.1.0",
      "lastUpdated": "2025-10-09"
    },
    {
      "id": "port",
      "name": "Port",
      "description": "port protocol on Solana",
      "category": "defi",
      "idlPath": "IDLs/portIDL.json",
      "repo": null,
      "status": "available",
      "version": "0.1.0",
      "lastUpdated": "2025-10-09"
    },
    {
      "id": "prism",
      "name": "Prism",
      "description": "prism protocol on Solana",
      "category": "defi",
      "idlPath": "IDLs/prismIDL.json",
      "repo": null,
      "status": "available",
      "version": "0.1.0",
      "lastUpdated": "2025-10-09"
    },
    {
      "id": "pumpfun",
      "name": "Pumpfun",
      "description": "pumpfun protocol on Solana",
      "category": "defi",
      "idlPath": "IDLs/pumpfunIDL.json",
      "repo": null,
      "status": "available",
      "version": "0.1.0",
      "lastUpdated": "2025-10-09"
    },
    {
      "id": "pumpswap",
      "name": "Pumpswap",
      "description": "pumpswap protocol on Solana",
      "category": "defi",
      "idlPath": "IDLs/pumpswapIDL.json",
      "repo": null,
      "status": "placeholder",
      "version": "0.1.0",
      "lastUpdated": "2025-10-09"
    },
    {
      "id": "quarry",
      "name": "Quarry",
      "description": "quarry protocol on Solana",
      "category": "defi",
      "idlPath": "IDLs/quarryIDL.json",
      "repo": null,
      "status": "available",
      "version": "0.1.0",
      "lastUpdated": "2025-10-09"
    },
    {
      "id": "ribbon",
      "name": "Ribbon",
      "description": "ribbon protocol on Solana",
      "category": "defi",
      "idlPath": "IDLs/ribbonIDL.json",
      "repo": null,
      "status": "available",
      "version": "0.1.0",
      "lastUpdated": "2025-10-09"
    },
    {
      "id": "saber",
      "name": "Saber",
      "description": "saber protocol on Solana",
      "category": "defi",
      "idlPath": "IDLs/saberIDL.json",
      "repo": null,
      "status": "available",
      "version": "0.1.0",
      "lastUpdated": "2025-10-09"
    },
    {
      "id": "saber-periphery",
      "name": "Saber periphery",
      "description": "saber-periphery protocol on Solana",
      "category": "defi",
      "idlPath": "IDLs/saber-peripheryIDL.json",
      "repo": null,
      "status": "available",
      "version": "0.1.0",
      "lastUpdated": "2025-10-09"
    },
    {
      "id": "sanctum",
      "name": "Sanctum",
      "description": "Liquid staking infrastructure",
      "category": "liquid-staking",
      "idlPath": "IDLs/sanctumIDL.json",
      "repo": null,
      "status": "available",
      "version": "0.1.0",
      "lastUpdated": "2025-10-09"
    },
    {
      "id": "saros",
      "name": "Saros",
      "description": "saros protocol on Solana",
      "category": "defi",
      "idlPath": "IDLs/sarosIDL.json",
      "repo": null,
      "status": "available",
      "version": "0.1.0",
      "lastUpdated": "2025-10-09"
    },
    {
      "id": "save",
      "name": "Save",
      "description": "save protocol on Solana",
      "category": "defi",
      "idlPath": "IDLs/saveIDL.json",
      "repo": null,
      "status": "placeholder",
      "version": "0.1.0",
      "lastUpdated": "2025-10-09"
    },
    {
      "id": "sencha",
      "name": "Sencha",
      "description": "sencha protocol on Solana",
      "category": "defi",
      "idlPath": "IDLs/senchaIDL.json",
      "repo": null,
      "status": "available",
      "version": "0.1.0",
      "lastUpdated": "2025-10-09"
    },
    {
      "id": "serum-v2",
      "name": "Serum v2",
      "description": "serum-v2 protocol on Solana",
      "category": "defi",
      "idlPath": "IDLs/serum-v2IDL.json",
      "repo": null,
      "status": "available",
      "version": "0.1.0",
      "lastUpdated": "2025-10-09"
    },
    {
      "id": "snapshots",
      "name": "Snapshots",
      "description": "snapshots protocol on Solana",
      "category": "defi",
      "idlPath": "IDLs/snapshotsIDL.json",
      "repo": null,
      "status": "placeholder",
      "version": "0.1.0",
      "lastUpdated": "2025-10-09"
    },
    {
      "id": "solanium",
      "name": "Solanium",
      "description": "solanium protocol on Solana",
      "category": "defi",
      "idlPath": "IDLs/solaniumIDL.json",
      "repo": null,
      "status": "available",
      "version": "0.1.0",
      "lastUpdated": "2025-10-09"
    },
    {
      "id": "solend",
      "name": "Solend",
      "description": "Algorithmic lending protocol",
      "category": "lending",
      "idlPath": "IDLs/solendIDL.json",
      "repo": null,
      "status": "available",
      "version": "0.1.0",
      "lastUpdated": "2025-10-09"
    },
    {
      "id": "solfi",
      "name": "Solfi",
      "description": "solfi protocol on Solana",
      "category": "defi",
      "idlPath": "IDLs/solfiIDL.json",
      "repo": null,
      "status": "placeholder",
      "version": "0.1.0",
      "lastUpdated": "2025-10-09"
    },
    {
      "id": "solrazr",
      "name": "Solrazr",
      "description": "solrazr protocol on Solana",
      "category": "defi",
      "idlPath": "IDLs/solrazrIDL.json",
      "repo": null,
      "status": "placeholder",
      "version": "0.1.0",
      "lastUpdated": "2025-10-09"
    },
    {
      "id": "solstarter",
      "name": "Solstarter",
      "description": "solstarter protocol on Solana",
      "category": "defi",
      "idlPath": "IDLs/solstarterIDL.json",
      "repo": null,
      "status": "placeholder",
      "version": "0.1.0",
      "lastUpdated": "2025-10-09"
    },
    {
      "id": "stabble",
      "name": "Stabble",
      "description": "stabble protocol on Solana",
      "category": "defi",
      "idlPath": "IDLs/stabbleIDL.json",
      "repo": null,
      "status": "placeholder",
      "version": "0.1.0",
      "lastUpdated": "2025-10-09"
    },
    {
      "id": "stable-swap",
      "name": "Stable swap",
      "description": "stable-swap protocol on Solana",
      "category": "defi",
      "idlPath": "IDLs/stable-swapIDL.json",
      "repo": null,
      "status": "available",
      "version": "0.1.0",
      "lastUpdated": "2025-10-09"
    },
    {
      "id": "starlaunch",
      "name": "Starlaunch",
      "description": "starlaunch protocol on Solana",
      "category": "defi",
      "idlPath": "IDLs/starlaunchIDL.json",
      "repo": null,
      "status": "placeholder",
      "version": "0.1.0",
      "lastUpdated": "2025-10-09"
    },
    {
      "id": "step",
      "name": "Step",
      "description": "step protocol on Solana",
      "category": "defi",
      "idlPath": "IDLs/stepIDL.json",
      "repo": null,
      "status": "available",
      "version": "0.1.0",
      "lastUpdated": "2025-10-09"
    },
    {
      "id": "stepn",
      "name": "Stepn",
      "description": "stepn protocol on Solana",
      "category": "defi",
      "idlPath": "IDLs/stepnIDL.json",
      "repo": null,
      "status": "placeholder",
      "version": "0.1.0",
      "lastUpdated": "2025-10-09"
    },
    {
      "id": "sunny",
      "name": "Sunny",
      "description": "sunny protocol on Solana",
      "category": "defi",
      "idlPath": "IDLs/sunnyIDL.json",
      "repo": null,
      "status": "available",
      "version": "0.1.0",
      "lastUpdated": "2025-10-09"
    },
    {
      "id": "switchboard",
      "name": "Switchboard",
      "description": "switchboard protocol on Solana",
      "category": "defi",
      "idlPath": "IDLs/switchboardIDL.json",
      "repo": null,
      "status": "available",
      "version": "0.1.0",
      "lastUpdated": "2025-10-09"
    },
    {
      "id": "symmetry",
      "name": "Symmetry",
      "description": "symmetry protocol on Solana",
      "category": "defi",
      "idlPath": "IDLs/symmetryIDL.json",
      "repo": null,
      "status": "available",
      "version": "0.1.0",
      "lastUpdated": "2025-10-09"
    },
    {
      "id": "synthetify",
      "name": "Synthetify",
      "description": "synthetify protocol on Solana",
      "category": "defi",
      "idlPath": "IDLs/synthetifyIDL.json",
      "repo": null,
      "status": "available",
      "version": "0.1.0",
      "lastUpdated": "2025-10-09"
    },
    {
      "id": "tesserav",
      "name": "Tesserav",
      "description": "tesserav protocol on Solana",
      "category": "defi",
      "idlPath": "IDLs/tesseravIDL.json",
      "repo": null,
      "status": "placeholder",
      "version": "0.1.0",
      "lastUpdated": "2025-10-09"
    },
    {
      "id": "titan",
      "name": "Titan",
      "description": "titan protocol on Solana",
      "category": "defi",
      "idlPath": "IDLs/titanIDL.json",
      "repo": null,
      "status": "placeholder",
      "version": "0.1.0",
      "lastUpdated": "2025-10-09"
    },
    {
      "id": "tribeca",
      "name": "Tribeca",
      "description": "tribeca protocol on Solana",
      "category": "defi",
      "idlPath": "IDLs/tribecaIDL.json",
      "repo": null,
      "status": "available",
      "version": "0.1.0",
      "lastUpdated": "2025-10-09"
    },
    {
      "id": "tulip",
      "name": "Tulip",
      "description": "tulip protocol on Solana",
      "category": "defi",
      "idlPath": "IDLs/tulipIDL.json",
      "repo": null,
      "status": "available",
      "version": "0.1.0",
      "lastUpdated": "2025-10-09"
    },
    {
      "id": "uxd",
      "name": "Uxd",
      "description": "uxd protocol on Solana",
      "category": "defi",
      "idlPath": "IDLs/uxdIDL.json",
      "repo": null,
      "status": "available",
      "version": "0.1.0",
      "lastUpdated": "2025-10-09"
    },
    {
      "id": "venko",
      "name": "Venko",
      "description": "venko protocol on Solana",
      "category": "defi",
      "idlPath": "IDLs/venkoIDL.json",
      "repo": null,
      "status": "placeholder",
      "version": "0.1.0",
      "lastUpdated": "2025-10-09"
    },
    {
      "id": "yi",
      "name": "Yi",
      "description": "yi protocol on Solana",
      "category": "defi",
      "idlPath": "IDLs/yiIDL.json",
      "repo": null,
      "status": "placeholder",
      "version": "0.1.0",
      "lastUpdated": "2025-10-09"
    },
    {
      "id": "zerofi",
      "name": "Zerofi",
      "description": "zerofi protocol on Solana",
      "category": "defi",
      "idlPath": "IDLs/zerofiIDL.json",
      "repo": null,
      "status": "placeholder",
      "version": "0.1.0",
      "lastUpdated": "2025-10-09"
    },
    {
      "id": "zeroone",
      "name": "Zeroone",
      "description": "zeroone protocol on Solana",
      "category": "defi",
      "idlPath": "IDLs/zerooneIDL.json",
      "repo": null,
      "status": "placeholder",
      "version": "0.1.0",
      "lastUpdated": "2025-10-09"
    },
    {
      "id": "zeta",
      "name": "Zeta Markets",
      "description": "Options and futures DEX",
      "category": "derivatives",
      "idlPath": "IDLs/zetaIDL.json",
      "repo": null,
      "status": "available",
      "version": "0.1.0",
      "lastUpdated": "2025-10-09"
    }
  ]
}